imgdl/__init__.py
imgdl/cli.py
imgdl/downloader.py
imgdl/settings.py
imgdl/utils.py
imgdl-2.0.1.dist-info/entry_points.txt
imgdl-2.0.1.dist-info/LICENSE
imgdl-2.0.1.dist-info/WHEEL
imgdl-2.0.1.dist-info/METADATA
imgdl-2.0.1.dist-info/RECORD
