Metadata-Version: 2.1
Name: imgdl
Version: 2.0.1
Summary: Bulk image downloader from a list of urls
Home-page: https://github.com/felipeam86/imagedownloader
License: MIT
Author: Felipe Aguirre Martinez
Author-email: felipeam86@gmail.com
Requires-Python: >=3.9,<4.0
Classifier: License :: OSI Approved :: MIT License
Classifier: Programming Language :: Python :: 3
Classifier: Programming Language :: Python :: 3.9
Classifier: Programming Language :: Python :: 3.10
Requires-Dist: Pillow (>=9.2.0,<10.0.0)
Requires-Dist: pydantic (>=1.10.2,<2.0.0)
Requires-Dist: python-json-logger (>=2.0.4,<3.0.0)
Requires-Dist: requests (>=2.28.1,<3.0.0)
Requires-Dist: tqdm (>=4.64.1,<5.0.0)
